pycorda/__init__.py
pycorda/core.py
pycorda/stats.py
pycorda-0.61.dist-info/LICENSE
pycorda-0.61.dist-info/METADATA
pycorda-0.61.dist-info/WHEEL
pycorda-0.61.dist-info/top_level.txt
pycorda-0.61.dist-info/RECORD
