Metadata-Version: 2.1
Name: pycorda
Version: 0.61
Summary: UNKNOWN
Home-page: UNKNOWN
Author: Jamiel Sheikh
Author-email: UNKNOWN
License: UNKNOWN
Platform: UNKNOWN
Requires-Dist: jaydebeapi
Requires-Dist: pandas
Requires-Dist: matplotlib
Requires-Dist: datetime
Requires-Dist: requests
Requires-Dist: pyjks
Requires-Dist: chart-studio
Requires-Dist: scikit-learn
Requires-Dist: jolokia
